{"version":"1.0","generated":"2025-08-29T20:18:34.568764Z","namespace":"ExportsSnapshots","tools":[{"operationId":"AdGroupExport","method":"POST","path":"/adGroups/export","preferred_name":"AdGroupExport","complexity":{"score":0,"factors":{"depth":0,"properties":0,"arrays":false},"threshold_exceeded":false,"reason":""}},{"operationId":"AdExport","method":"POST","path":"/ads/export","preferred_name":"AdExport","complexity":{"score":0,"factors":{"depth":0,"properties":0,"arrays":false},"threshold_exceeded":false,"reason":""}},{"operationId":"CampExport","method":"POST","path":"/campaigns/export","preferred_name":"CampExport","complexity":{"score":0,"factors":{"depth":0,"properties":0,"arrays":false},"threshold_exceeded":false,"reason":""}},{"operationId":"GetExport","method":"GET","path":"/exports/{exportId}","preferred_name":"GetExport","complexity":{"score":0,"factors":{"depth":0,"properties":0,"arrays":false},"threshold_exceeded":false,"reason":""}},{"operationId":"TargetExport","method":"POST","path":"/targets/export","preferred_name":"TargetExport","complexity":{"score":0,"factors":{"depth":0,"properties":0,"arrays":false},"threshold_exceeded":false,"reason":""}}]}