{"requests":{"POST /sp/campaignNegativeKeywords":"application/vnd.spCampaignNegativeKeyword.v3+json","PUT /sp/campaignNegativeKeywords":"application/vnd.spCampaignNegativeKeyword.v3+json","POST /sp/campaignNegativeKeywords/delete":"application/vnd.spCampaignNegativeKeyword.v3+json","POST /sp/campaignNegativeKeywords/list":"application/vnd.spCampaignNegativeKeyword.v3+json","POST /sp/negativeKeywords":"application/vnd.spNegativeKeyword.v3+json","PUT /sp/negativeKeywords":"application/vnd.spNegativeKeyword.v3+json","POST /sp/negativeKeywords/delete":"application/vnd.spNegativeKeyword.v3+json","POST /sp/negativeKeywords/list":"application/vnd.spNegativeKeyword.v3+json"},"responses":{"POST /sp/campaignNegativeKeywords":["application/json","application/vnd.spCampaignNegativeKeyword.v3+json"],"PUT /sp/campaignNegativeKeywords":["application/json","application/vnd.spCampaignNegativeKeyword.v3+json"],"POST /sp/campaignNegativeKeywords/delete":["application/json","application/vnd.spCampaignNegativeKeyword.v3+json"],"POST /sp/campaignNegativeKeywords/list":["application/json","application/vnd.spCampaignNegativeKeyword.v3+json"],"POST /sp/negativeKeywords":["application/json","application/vnd.spNegativeKeyword.v3+json"],"PUT /sp/negativeKeywords":["application/json","application/vnd.spNegativeKeyword.v3+json"],"POST /sp/negativeKeywords/delete":["application/json","application/vnd.spNegativeKeyword.v3+json"],"POST /sp/negativeKeywords/list":["application/json","application/vnd.spNegativeKeyword.v3+json"]}}